{"protocol":{"minReaderVersion":1,"minWriterVersion":2}}
{"metaData":{"id":"84c90c59-e5b9-4340-ba13-743268fbffa4","name":null,"description":null,"format":{"provider":"parquet","options":{}},"schemaString":"{\"type\":\"struct\",\"fields\":[{\"name\":\"date\",\"type\":\"string\",\"nullable\":false,\"metadata\":{}},{\"name\":\"private_fixed_investment\",\"type\":\"double\",\"nullable\":true,\"metadata\":{}},{\"name\":\"nonresidential\",\"type\":\"double\",\"nullable\":true,\"metadata\":{}},{\"name\":\"structures\",\"type\":\"double\",\"nullable\":true,\"metadata\":{}},{\"name\":\"commercial_and_health_care\",\"type\":\"double\",\"nullable\":true,\"metadata\":{}},{\"name\":\"manufacturing\",\"type\":\"double\",\"nullable\":true,\"metadata\":{}},{\"name\":\"power_and_communication\",\"type\":\"double\",\"nullable\":true,\"metadata\":{}},{\"name\":\"mining_exploration_shafts_and_wells\",\"type\":\"double\",\"nullable\":true,\"metadata\":{}},{\"name\":\"other_structures\",\"type\":\"double\",\"nullable\":true,\"metadata\":{}},{\"name\":\"equipment\",\"type\":\"double\",\"nullable\":true,\"metadata\":{}},{\"name\":\"information_processing_equipment\",\"type\":\"double\",\"nullable\":true,\"metadata\":{}},{\"name\":\"computers_and_peripheral_equipment\",\"type\":\"double\",\"nullable\":true,\"metadata\":{}},{\"name\":\"other\",\"type\":\"double\",\"nullable\":true,\"metadata\":{}},{\"name\":\"industrial_equipment\",\"type\":\"double\",\"nullable\":true,\"metadata\":{}},{\"name\":\"transportation_equipment\",\"type\":\"double\",\"nullable\":true,\"metadata\":{}},{\"name\":\"other_equipment\",\"type\":\"double\",\"nullable\":true,\"metadata\":{}},{\"name\":\"intellectual_property_products\",\"type\":\"double\",\"nullable\":true,\"metadata\":{}},{\"name\":\"software\",\"type\":\"double\",\"nullable\":true,\"metadata\":{}},{\"name\":\"research_and_development\",\"type\":\"double\",\"nullable\":true,\"metadata\":{}},{\"name\":\"entertainment_literary_and_artistic_originals\",\"type\":\"double\",\"nullable\":true,\"metadata\":{}},{\"name\":\"residential\",\"type\":\"double\",\"nullable\":true,\"metadata\":{}},{\"name\":\"permanent_site\",\"type\":\"double\",\"nullable\":true,\"metadata\":{}},{\"name\":\"single_family\",\"type\":\"double\",\"nullable\":true,\"metadata\":{}},{\"name\":\"multifamily\",\"type\":\"double\",\"nullable\":true,\"metadata\":{}},{\"name\":\"private_fixed_investment_in_structures\",\"type\":\"double\",\"nullable\":true,\"metadata\":{}},{\"name\":\"private_fixed_investment_in_new_structures\",\"type\":\"double\",\"nullable\":true,\"metadata\":{}},{\"name\":\"nonresidential_structures\",\"type\":\"double\",\"nullable\":true,\"metadata\":{}},{\"name\":\"residential_structures\",\"type\":\"double\",\"nullable\":true,\"metadata\":{}},{\"name\":\"private_fixed_investment_in_information_processing_equipment_and_software\",\"type\":\"double\",\"nullable\":true,\"metadata\":{}}]}","partitionColumns":[],"createdTime":1764958753554,"configuration":{}}}
{"add":{"path":"part-00000-4c380638-1014-475d-8918-ead3f797bca4-c000.snappy.parquet","partitionValues":{},"size":63435,"modificationTime":1764958753556,"dataChange":true,"stats":"{\"numRecords\":314,\"minValues\":{\"private_fixed_investment_in_structures\":18132.0,\"permanent_site\":14526.0,\"research_and_development\":952.0,\"single_family\":12352.0,\"information_processing_equipment\":1525.0,\"private_fixed_investment_in_new_structures\":37793.0,\"residential_structures\":20243.0,\"mining_exploration_shafts_and_wells\":2158.0,\"transportation_equipment\":4675.0,\"private_fixed_investment\":35359.0,\"manufacturing\":1884.0,\"multifamily\":2174.0,\"computers_and_peripheral_equipment\":2.0,\"nonresidential_structures\":17219.0,\"nonresidential\":24818.0,\"other\":1525.0,\"entertainment_literary_and_artistic_originals\":919.0,\"commercial_and_health_care\":4140.0,\"other_structures\":6370.0,\"software\":5.0,\"power_and_communication\":4004.0,\"equipment\":282.0,\"structures\":10243.0,\"date\":\"1947-Q1\",\"private_fixed_investment_in_information_processing_equipment_and_software\":1525.0,\"industrial_equipment\":3236.0,\"other_equipment\":3815.0,\"residential\":10541.0,\"intellectual_property_products\":1998.0},\"maxValues\":{\"private_fixed_investment_in_structures\":2101563.0,\"commercial_and_health_care\":299239.0,\"other_equipment\":328144.0,\"entertainment_literary_and_artistic_originals\":115495.0,\"software\":745934.0,\"other_structures\":638050.0,\"private_fixed_investment_in_information_processing_equipment_and_software\":1352452.0,\"manufacturing\":238621.0,\"structures\":1200294.0,\"mining_exploration_shafts_and_wells\":192877.0,\"private_fixed_investment_in_new_structures\":1886980.0,\"other\":362345.0,\"nonresidential_structures\":920914.0,\"intellectual_property_products\":1691198.0,\"date\":\"2025-Q2\",\"power_and_communication\":172370.0,\"research_and_development\":829769.0,\"private_fixed_investment\":5404422.0,\"nonresidential\":4207512.0,\"equipment\":21906.0,\"residential\":1222200.0,\"residential_structures\":1008447.0,\"multifamily\":141937.0,\"transportation_equipment\":366677.0,\"information_processing_equipment\":606518.0,\"computers_and_peripheral_equipment\":253788.0,\"permanent_site\":600062.0,\"industrial_equipment\":337999.0,\"single_family\":489552.0},\"nullCount\":{\"industrial_equipment\":0,\"transportation_equipment\":0,\"date\":0,\"entertainment_literary_and_artistic_originals\":0,\"structures\":0,\"commercial_and_health_care\":44,\"research_and_development\":0,\"private_fixed_investment_in_new_structures\":44,\"residential_structures\":44,\"manufacturing\":44,\"nonresidential_structures\":44,\"software\":48,\"residential\":0,\"equipment\":0,\"single_family\":44,\"private_fixed_investment_in_information_processing_equipment_and_software\":0,\"permanent_site\":44,\"other\":0,\"other_equipment\":0,\"information_processing_equipment\":0,\"other_structures\":44,\"computers_and_peripheral_equipment\":48,\"intellectual_property_products\":0,\"nonresidential\":0,\"power_and_communication\":44,\"mining_exploration_shafts_and_wells\":44,\"private_fixed_investment\":0,\"private_fixed_investment_in_structures\":0,\"multifamily\":44}}","tags":null,"baseRowId":null,"defaultRowCommitVersion":null,"clusteringProvider":null}}
{"commitInfo":{"timestamp":1764958753556,"operation":"WRITE","operationParameters":{"mode":"Overwrite"},"engineInfo":"delta-rs:py-1.2.1","clientVersion":"delta-rs.py-1.2.1","operationMetrics":{"execution_time_ms":2,"num_added_files":1,"num_added_rows":314,"num_partitions":0,"num_removed_files":0}}}