{"protocol":{"minReaderVersion":1,"minWriterVersion":2}}
{"metaData":{"id":"70708b9c-2fd9-4d01-a835-73fe0770a314","name":null,"description":null,"format":{"provider":"parquet","options":{}},"schemaString":"{\"type\":\"struct\",\"fields\":[{\"name\":\"date\",\"type\":\"string\",\"nullable\":false,\"metadata\":{}},{\"name\":\"personal_consumption_expenditures\",\"type\":\"double\",\"nullable\":true,\"metadata\":{}},{\"name\":\"goods\",\"type\":\"double\",\"nullable\":true,\"metadata\":{}},{\"name\":\"durable_goods\",\"type\":\"double\",\"nullable\":true,\"metadata\":{}},{\"name\":\"motor_vehicles_and_parts\",\"type\":\"double\",\"nullable\":true,\"metadata\":{}},{\"name\":\"new_motor_vehicles\",\"type\":\"double\",\"nullable\":true,\"metadata\":{}},{\"name\":\"net_purchases_of_used_motor_vehicles\",\"type\":\"double\",\"nullable\":true,\"metadata\":{}},{\"name\":\"motor_vehicle_parts_and_accessories\",\"type\":\"double\",\"nullable\":true,\"metadata\":{}},{\"name\":\"furnishings_and_durable_household_equipment\",\"type\":\"double\",\"nullable\":true,\"metadata\":{}},{\"name\":\"furniture_and_furnishings\",\"type\":\"double\",\"nullable\":true,\"metadata\":{}},{\"name\":\"household_appliances\",\"type\":\"double\",\"nullable\":true,\"metadata\":{}},{\"name\":\"glassware_tableware_and_household_utensils\",\"type\":\"double\",\"nullable\":true,\"metadata\":{}},{\"name\":\"tools_and_equipment_for_house_and_garden\",\"type\":\"double\",\"nullable\":true,\"metadata\":{}},{\"name\":\"recreational_goods_and_vehicles\",\"type\":\"double\",\"nullable\":true,\"metadata\":{}},{\"name\":\"video_audio_photographic_and_information_processing_equipment_and_media\",\"type\":\"double\",\"nullable\":true,\"metadata\":{}},{\"name\":\"sporting_equipment_supplies_guns_and_ammunition\",\"type\":\"double\",\"nullable\":true,\"metadata\":{}},{\"name\":\"sports_and_recreational_vehicles\",\"type\":\"double\",\"nullable\":true,\"metadata\":{}},{\"name\":\"recreational_books\",\"type\":\"double\",\"nullable\":true,\"metadata\":{}},{\"name\":\"musical_instruments\",\"type\":\"double\",\"nullable\":true,\"metadata\":{}},{\"name\":\"other_durable_goods\",\"type\":\"double\",\"nullable\":true,\"metadata\":{}},{\"name\":\"jewelry_and_watches\",\"type\":\"double\",\"nullable\":true,\"metadata\":{}},{\"name\":\"therapeutic_appliances_and_equipment\",\"type\":\"double\",\"nullable\":true,\"metadata\":{}},{\"name\":\"educational_books\",\"type\":\"double\",\"nullable\":true,\"metadata\":{}},{\"name\":\"luggage_and_similar_personal_items\",\"type\":\"double\",\"nullable\":true,\"metadata\":{}},{\"name\":\"telephone_and_related_communication_equipment\",\"type\":\"double\",\"nullable\":true,\"metadata\":{}},{\"name\":\"nondurable_goods\",\"type\":\"double\",\"nullable\":true,\"metadata\":{}},{\"name\":\"food_and_beverages_purchased_for_offpremises_consumption\",\"type\":\"double\",\"nullable\":true,\"metadata\":{}},{\"name\":\"food_and_nonalcoholic_beverages_purchased_for_offpremises_consumption\",\"type\":\"double\",\"nullable\":true,\"metadata\":{}},{\"name\":\"alcoholic_beverages_purchased_for_offpremises_consumption\",\"type\":\"double\",\"nullable\":true,\"metadata\":{}},{\"name\":\"food_produced_and_consumed_on_farms\",\"type\":\"double\",\"nullable\":true,\"metadata\":{}},{\"name\":\"clothing_and_footwear\",\"type\":\"double\",\"nullable\":true,\"metadata\":{}},{\"name\":\"garments\",\"type\":\"double\",\"nullable\":true,\"metadata\":{}},{\"name\":\"womens_and_girls_clothing\",\"type\":\"double\",\"nullable\":true,\"metadata\":{}},{\"name\":\"mens_and_boys_clothing\",\"type\":\"double\",\"nullable\":true,\"metadata\":{}},{\"name\":\"childrens_and_infants_clothing\",\"type\":\"double\",\"nullable\":true,\"metadata\":{}},{\"name\":\"other_clothing_materials_and_footwear\",\"type\":\"double\",\"nullable\":true,\"metadata\":{}},{\"name\":\"gasoline_and_other_energy_goods\",\"type\":\"double\",\"nullable\":true,\"metadata\":{}},{\"name\":\"motor_vehicle_fuels_lubricants_and_fluids\",\"type\":\"double\",\"nullable\":true,\"metadata\":{}},{\"name\":\"fuel_oil_and_other_fuels\",\"type\":\"double\",\"nullable\":true,\"metadata\":{}},{\"name\":\"other_nondurable_goods\",\"type\":\"double\",\"nullable\":true,\"metadata\":{}},{\"name\":\"pharmaceutical_and_other_medical_products\",\"type\":\"double\",\"nullable\":true,\"metadata\":{}},{\"name\":\"recreational_items\",\"type\":\"double\",\"nullable\":true,\"metadata\":{}},{\"name\":\"household_supplies\",\"type\":\"double\",\"nullable\":true,\"metadata\":{}},{\"name\":\"personal_care_products\",\"type\":\"double\",\"nullable\":true,\"metadata\":{}},{\"name\":\"tobacco\",\"type\":\"double\",\"nullable\":true,\"metadata\":{}},{\"name\":\"magazines_newspapers_and_stationery\",\"type\":\"double\",\"nullable\":true,\"metadata\":{}},{\"name\":\"services\",\"type\":\"double\",\"nullable\":true,\"metadata\":{}},{\"name\":\"household_consumption_expenditures_for_services\",\"type\":\"double\",\"nullable\":true,\"metadata\":{}},{\"name\":\"housing_and_utilities\",\"type\":\"double\",\"nullable\":true,\"metadata\":{}},{\"name\":\"housing\",\"type\":\"double\",\"nullable\":true,\"metadata\":{}},{\"name\":\"rental_of_tenantoccupied_nonfarm_housing\",\"type\":\"double\",\"nullable\":true,\"metadata\":{}},{\"name\":\"imputed_rental_of_owneroccupied_nonfarm_housing\",\"type\":\"double\",\"nullable\":true,\"metadata\":{}},{\"name\":\"rental_value_of_farm_dwellings\",\"type\":\"double\",\"nullable\":true,\"metadata\":{}},{\"name\":\"group_housing\",\"type\":\"double\",\"nullable\":true,\"metadata\":{}},{\"name\":\"household_utilities\",\"type\":\"double\",\"nullable\":true,\"metadata\":{}},{\"name\":\"water_supply_and_sanitation\",\"type\":\"double\",\"nullable\":true,\"metadata\":{}},{\"name\":\"electricity_and_gas\",\"type\":\"double\",\"nullable\":true,\"metadata\":{}},{\"name\":\"electricity\",\"type\":\"double\",\"nullable\":true,\"metadata\":{}},{\"name\":\"natural_gas\",\"type\":\"double\",\"nullable\":true,\"metadata\":{}},{\"name\":\"health_care\",\"type\":\"double\",\"nullable\":true,\"metadata\":{}},{\"name\":\"outpatient_services\",\"type\":\"double\",\"nullable\":true,\"metadata\":{}},{\"name\":\"physician_services\",\"type\":\"double\",\"nullable\":true,\"metadata\":{}},{\"name\":\"dental_services\",\"type\":\"double\",\"nullable\":true,\"metadata\":{}},{\"name\":\"paramedical_services\",\"type\":\"double\",\"nullable\":true,\"metadata\":{}},{\"name\":\"hospital_and_nursing_home_services\",\"type\":\"double\",\"nullable\":true,\"metadata\":{}},{\"name\":\"hospitals\",\"type\":\"double\",\"nullable\":true,\"metadata\":{}},{\"name\":\"nursing_homes\",\"type\":\"double\",\"nullable\":true,\"metadata\":{}},{\"name\":\"transportation_services\",\"type\":\"double\",\"nullable\":true,\"metadata\":{}},{\"name\":\"motor_vehicle_services\",\"type\":\"double\",\"nullable\":true,\"metadata\":{}},{\"name\":\"motor_vehicle_maintenance_and_repair\",\"type\":\"double\",\"nullable\":true,\"metadata\":{}},{\"name\":\"other_motor_vehicle_services\",\"type\":\"double\",\"nullable\":true,\"metadata\":{}},{\"name\":\"public_transportation\",\"type\":\"double\",\"nullable\":true,\"metadata\":{}},{\"name\":\"ground_transportation\",\"type\":\"double\",\"nullable\":true,\"metadata\":{}},{\"name\":\"air_transportation\",\"type\":\"double\",\"nullable\":true,\"metadata\":{}},{\"name\":\"water_transportation\",\"type\":\"double\",\"nullable\":true,\"metadata\":{}},{\"name\":\"recreation_services\",\"type\":\"double\",\"nullable\":true,\"metadata\":{}},{\"name\":\"membership_clubs_sports_centers_parks_theaters_and_museums\",\"type\":\"double\",\"nullable\":true,\"metadata\":{}},{\"name\":\"audiovideo_photographic_and_information_processing_equipment_services\",\"type\":\"double\",\"nullable\":true,\"metadata\":{}},{\"name\":\"gambling\",\"type\":\"double\",\"nullable\":true,\"metadata\":{}},{\"name\":\"other_recreational_services\",\"type\":\"double\",\"nullable\":true,\"metadata\":{}},{\"name\":\"food_services_and_accommodations\",\"type\":\"double\",\"nullable\":true,\"metadata\":{}},{\"name\":\"food_services\",\"type\":\"double\",\"nullable\":true,\"metadata\":{}},{\"name\":\"purchased_meals_and_beverages\",\"type\":\"double\",\"nullable\":true,\"metadata\":{}},{\"name\":\"food_furnished_to_employees_including_military\",\"type\":\"double\",\"nullable\":true,\"metadata\":{}},{\"name\":\"accommodations\",\"type\":\"double\",\"nullable\":true,\"metadata\":{}},{\"name\":\"financial_services_and_insurance\",\"type\":\"double\",\"nullable\":true,\"metadata\":{}},{\"name\":\"financial_services\",\"type\":\"double\",\"nullable\":true,\"metadata\":{}},{\"name\":\"financial_services_furnished_without_payment\",\"type\":\"double\",\"nullable\":true,\"metadata\":{}},{\"name\":\"financial_service_charges_fees_and_commissions\",\"type\":\"double\",\"nullable\":true,\"metadata\":{}},{\"name\":\"insurance\",\"type\":\"double\",\"nullable\":true,\"metadata\":{}},{\"name\":\"life_insurance\",\"type\":\"double\",\"nullable\":true,\"metadata\":{}},{\"name\":\"net_household_insurance\",\"type\":\"double\",\"nullable\":true,\"metadata\":{}},{\"name\":\"net_health_insurance\",\"type\":\"double\",\"nullable\":true,\"metadata\":{}},{\"name\":\"net_motor_vehicle_and_other_transportation_insurance\",\"type\":\"double\",\"nullable\":true,\"metadata\":{}},{\"name\":\"other_services\",\"type\":\"double\",\"nullable\":true,\"metadata\":{}},{\"name\":\"communication\",\"type\":\"double\",\"nullable\":true,\"metadata\":{}},{\"name\":\"telecommunication_services\",\"type\":\"double\",\"nullable\":true,\"metadata\":{}},{\"name\":\"postal_and_delivery_services\",\"type\":\"double\",\"nullable\":true,\"metadata\":{}},{\"name\":\"internet_access\",\"type\":\"double\",\"nullable\":true,\"metadata\":{}},{\"name\":\"education_services\",\"type\":\"double\",\"nullable\":true,\"metadata\":{}},{\"name\":\"higher_education\",\"type\":\"double\",\"nullable\":true,\"metadata\":{}},{\"name\":\"nursery_elementary_and_secondary_schools\",\"type\":\"double\",\"nullable\":true,\"metadata\":{}},{\"name\":\"commercial_and_vocational_schools\",\"type\":\"double\",\"nullable\":true,\"metadata\":{}},{\"name\":\"professional_and_other_services\",\"type\":\"double\",\"nullable\":true,\"metadata\":{}},{\"name\":\"personal_care_and_clothing_services\",\"type\":\"double\",\"nullable\":true,\"metadata\":{}},{\"name\":\"social_services_and_religious_activities\",\"type\":\"double\",\"nullable\":true,\"metadata\":{}},{\"name\":\"household_maintenance\",\"type\":\"double\",\"nullable\":true,\"metadata\":{}},{\"name\":\"foreign_travel_by_us_residents\",\"type\":\"double\",\"nullable\":true,\"metadata\":{}},{\"name\":\"less_expenditures_in_the_united_states_by_nonresidents\",\"type\":\"double\",\"nullable\":true,\"metadata\":{}},{\"name\":\"final_consumption_expenditures_of_nonprofit_institutions_serving_households_npishs\",\"type\":\"double\",\"nullable\":true,\"metadata\":{}},{\"name\":\"gross_output_of_nonprofit_institutions\",\"type\":\"double\",\"nullable\":true,\"metadata\":{}},{\"name\":\"less_receipts_from_sales_of_goods_and_services_by_nonprofit_institutions\",\"type\":\"double\",\"nullable\":true,\"metadata\":{}}]}","partitionColumns":[],"createdTime":1767341233496,"configuration":{}}}
{"add":{"path":"part-00000-dc6dbaf7-ad8d-4c3c-ab3f-0f751e3cc6dc-c000.snappy.parquet","partitionValues":{},"size":131517,"modificationTime":1767341233656,"dataChange":true,"stats":"{\"numRecords\":314,\"minValues\":{\"new_motor_vehicles\":-8.5,\"furniture_and_furnishings\":-7.9,\"glassware_tableware_and_household_utensils\":-19.1,\"motor_vehicle_parts_and_accessories\":-18.2,\"food_produced_and_consumed_on_farms\":-49.4,\"telephone_and_related_communication_equipment\":-26.7,\"nondurable_goods\":-22.5,\"recreational_goods_and_vehicles\":-11.4,\"household_appliances\":-12.7,\"motor_vehicles_and_parts\":-22.7,\"garments\":-22.3,\"educational_books\":-7.7,\"video_audio_photographic_and_information_processing_equipment_and_media\":-19.1,\"jewelry_and_watches\":-12.8,\"alcoholic_beverages_purchased_for_offpremises_consumption\":-3.0,\"net_purchases_of_used_motor_vehicles\":-16.8,\"furnishings_and_durable_household_equipment\":-7.6,\"sporting_equipment_supplies_guns_and_ammunition\":-12.5,\"sports_and_recreational_vehicles\":-10.1,\"food_and_nonalcoholic_beverages_purchased_for_offpremises_consumption\":-4.5,\"therapeutic_appliances_and_equipment\":-12.1,\"durable_goods\":-9.7,\"recreational_books\":-13.4,\"luggage_and_similar_personal_items\":-21.8,\"goods\":-16.7,\"other_durable_goods\":-11.3,\"food_and_beverages_purchased_for_offpremises_consumption\":-8.7,\"tools_and_equipment_for_house_and_garden\":-12.2,\"clothing_and_footwear\":-21.3,\"personal_consumption_expenditures\":-6.2,\"musical_instruments\":-9.3,\"date\":\"1947-Q2\"},\"maxValues\":{\"educational_books\":38.2,\"goods\":17.3,\"date\":\"2025-Q3\",\"durable_goods\":16.1,\"recreational_books\":75.5,\"alcoholic_beverages_purchased_for_offpremises_consumption\":39.0,\"luggage_and_similar_personal_items\":41.9,\"personal_consumption_expenditures\":13.3,\"motor_vehicles_and_parts\":35.0,\"clothing_and_footwear\":15.4,\"garments\":14.0,\"telephone_and_related_communication_equipment\":38.4,\"tools_and_equipment_for_house_and_garden\":16.2,\"furniture_and_furnishings\":18.0,\"musical_instruments\":14.1,\"other_durable_goods\":32.2,\"nondurable_goods\":22.3,\"food_and_nonalcoholic_beverages_purchased_for_offpremises_consumption\":22.9,\"food_produced_and_consumed_on_farms\":71.0,\"recreational_goods_and_vehicles\":11.5,\"jewelry_and_watches\":41.7,\"video_audio_photographic_and_information_processing_equipment_and_media\":12.7,\"new_motor_vehicles\":19.1,\"therapeutic_appliances_and_equipment\":11.7,\"sporting_equipment_supplies_guns_and_ammunition\":16.3,\"sports_and_recreational_vehicles\":22.5,\"food_and_beverages_purchased_for_offpremises_consumption\":24.9,\"motor_vehicle_parts_and_accessories\":20.6,\"net_purchases_of_used_motor_vehicles\":83.4,\"household_appliances\":24.5,\"furnishings_and_durable_household_equipment\":19.6,\"glassware_tableware_and_household_utensils\":27.9},\"nullCount\":{\"personal_consumption_expenditures\":0,\"food_produced_and_consumed_on_farms\":48,\"goods\":0,\"date\":0,\"musical_instruments\":48,\"motor_vehicles_and_parts\":0,\"furnishings_and_durable_household_equipment\":0,\"household_appliances\":48,\"new_motor_vehicles\":48,\"telephone_and_related_communication_equipment\":48,\"food_and_beverages_purchased_for_offpremises_consumption\":0,\"durable_goods\":0,\"motor_vehicle_parts_and_accessories\":48,\"video_audio_photographic_and_information_processing_equipment_and_media\":48,\"educational_books\":48,\"jewelry_and_watches\":48,\"clothing_and_footwear\":0,\"furniture_and_furnishings\":48,\"tools_and_equipment_for_house_and_garden\":48,\"recreational_books\":48,\"alcoholic_beverages_purchased_for_offpremises_consumption\":48,\"sports_and_recreational_vehicles\":48,\"glassware_tableware_and_household_utensils\":48,\"other_durable_goods\":0,\"garments\":48,\"nondurable_goods\":0,\"food_and_nonalcoholic_beverages_purchased_for_offpremises_consumption\":48,\"therapeutic_appliances_and_equipment\":48,\"sporting_equipment_supplies_guns_and_ammunition\":48,\"recreational_goods_and_vehicles\":0,\"luggage_and_similar_personal_items\":48,\"net_purchases_of_used_motor_vehicles\":48}}","tags":null,"baseRowId":null,"defaultRowCommitVersion":null,"clusteringProvider":null}}
{"commitInfo":{"timestamp":1767341233656,"operation":"WRITE","operationParameters":{"mode":"Overwrite"},"engineInfo":"delta-rs:py-1.2.1","operationMetrics":{"execution_time_ms":160,"num_added_files":1,"num_added_rows":314,"num_partitions":0,"num_removed_files":0},"clientVersion":"delta-rs.py-1.2.1"}}